emod_malaria/Eradication.zip
emod_malaria/__init__.py
emod_malaria/bootstrap.py
emod_malaria/schema.zip
emod_malaria-2.31.0.dist-info/METADATA
emod_malaria-2.31.0.dist-info/WHEEL
emod_malaria-2.31.0.dist-info/top_level.txt
emod_malaria-2.31.0.dist-info/RECORD
