Metadata-Version: 2.4
Name: emod-malaria
Version: 2.31.0
Summary: PyPI distribution of EMOD for the Malaria sim type
License-Expression: MIT
Project-URL: Documentation, https://docs.idmod.org/projects/emod/en/latest/
Project-URL: Repository, https://github.com/EMOD-Hub/EMOD
Project-URL: Issues, https://github.com/EMOD-Hub/EMOD/issues
Classifier: Operating System :: POSIX :: Linux
Classifier: Programming Language :: C++
Classifier: Topic :: Scientific/Engineering :: Bio-Informatics
Requires-Python: >=3.9
Provides-Extra: docs
Provides-Extra: tests
